{
  "Routes": [
    {
      "UpstreamPathTemplate": "/gateway/auth/{everything}",
      "UpstreamHttpMethod": [ "Post" ],
      "DownstreamScheme": "https",
      "DownstreamPathTemplate": "/api/auth/{everything}",
      "DownstreamHostAndPorts": [
        {
          "Host": "localhost",
          "Port": 7001
        }
      ],
      "SwaggerKey": "auth"
    },
    {
      "UpstreamPathTemplate": "/gateway/products",
      "UpstreamHttpMethod": [ "Get", "Post", "Delete" ],
      "DownstreamPathTemplate": "/api/products",
      "DownstreamScheme": "https",
      "DownstreamHostAndPorts": [
        {
          "Host": "localhost",
          "Port": 7002
        }
      ],
      "SwaggerKey": "products",
      "AuthenticationOptions": {
        "AuthenticationProviderKey": "Bearer"
      }
    }
  ],
  "GlobalConfiguration": {
    "BaseUrl": "https://localhost:7000"
  },
  "SwaggerEndPoints": [
    {
      "Key": "auth",
      "Config": [
        {
          "Name": "Auth API",
          "Version": "v1",
          "Url": "https://localhost:7001/swagger/v1/swagger.json"
        }
      ]
    },
    {
      "Key": "products",
      "Config": [
        {
          "Name": "Products API",
          "Version": "v1",
          "Url": "https://localhost:7002/swagger/v1/swagger.json"
        }
      ]
    }
  ]
}